{
  "spec_version": "0.1.0",
  "source_hash": "cb9912e83739f0919cb9565fd625e4b0162a6075c7685ad8b20c2117dc40336d",
  "crate_name": "oid-registry",
  "crate_version": "0.8.1",
  "analysis_tier": "syntactic",
  "timestamp": 1776908702,
  "profile": {
    "findings": [
      {
        "capability": "file_read",
        "location": {
          "file": "./src/load.rs",
          "line": 2,
          "column": 1
        },
        "evidence": "std::fs::File",
        "origin": "import"
      }
    ]
  }
}
