{
  "spec_version": "0.1.0",
  "source_hash": "9bacefbe03ff23efd66d3699850ade9f9bd2ddfa900567ac3132fd224a3f857d",
  "crate_name": "phf_macros",
  "crate_version": "0.11.3",
  "analysis_tier": "syntactic",
  "timestamp": 1776908702,
  "profile": {
    "findings": [
      {
        "capability": "proc_macro",
        "location": {
          "file": "./src/lib.rs",
          "line": 306,
          "column": 1
        },
        "evidence": "#[proc_macro]",
        "origin": "attribute"
      },
      {
        "capability": "proc_macro",
        "location": {
          "file": "./src/lib.rs",
          "line": 314,
          "column": 1
        },
        "evidence": "#[proc_macro]",
        "origin": "attribute"
      },
      {
        "capability": "proc_macro",
        "location": {
          "file": "./src/lib.rs",
          "line": 323,
          "column": 1
        },
        "evidence": "#[proc_macro]",
        "origin": "attribute"
      },
      {
        "capability": "proc_macro",
        "location": {
          "file": "./src/lib.rs",
          "line": 331,
          "column": 1
        },
        "evidence": "#[proc_macro]",
        "origin": "attribute"
      }
    ]
  }
}
